transform_format_lib/TransformFormatLib1.cp313-win_amd64.pyd
transform_format_lib/TransformFormatLib1.pyi
transform_format_lib/__init__.py
transform_format_lib-0.1.0.dist-info/METADATA
transform_format_lib-0.1.0.dist-info/WHEEL
transform_format_lib-0.1.0.dist-info/top_level.txt
transform_format_lib-0.1.0.dist-info/RECORD
