Metadata-Version: 2.4
Name: transform-format-lib
Version: 0.1.0
Summary: GeoSun TransformFormat 基础库
Author-email: "wenxi.da" <wenxi.da007@qq.com>
License: MIT
Classifier: Development Status :: 3 - Alpha
Classifier: Intended Audience :: Developers
Classifier: License :: OSI Approved :: MIT License
Classifier: Programming Language :: Python :: 3
Classifier: Operating System :: Microsoft :: Windows
Requires-Python: >=3.9
